<authomata>
	<type>
		<item>AutomataFND</item>
	</type>
	<alphabet>
		<item>a</item>
		<item>b</item>
		<item>/</item>
	</alphabet>
	<states>
		<state>S0</state>
		<state>S1</state>
		<state>S2</state>
		<state>S3</state>
		<state>S4</state>
		<state>S5</state>
	</states>
	<init>
		<state>S4</state>
	</init>
	<finals>
		<state>S5</state>
	</finals>
	<arrows>
		<arrow>
		<state>S0</state>
		<state>S1</state>
		<item>a</item>
	</arrow>
		<arrow>
		<state>S1</state>
		<state>S5</state>
		<item>/</item>
	</arrow>
		<arrow>
		<state>S2</state>
		<state>S3</state>
		<item>b</item>
	</arrow>
		<arrow>
		<state>S3</state>
		<state>S5</state>
		<item>/</item>
	</arrow>
		<arrow>
		<state>S4</state>
		<state>S0</state>
		<item>/</item>
	</arrow>
		<arrow>
		<state>S4</state>
		<state>S2</state>
		<item>/</item>
	</arrow>
	</arrows>
<coordenadas>
<estadoCoord><nombre>S0</nombre><x>460</x><y>410</y></estadoCoord><estadoCoord><nombre>S1</nombre><x>598</x><y>330</y></estadoCoord><estadoCoord><nombre>S2</nombre><x>598</x><y>171</y></estadoCoord><estadoCoord><nombre>S3</nombre><x>460</x><y>90</y></estadoCoord><estadoCoord><nombre>S4</nombre><x>322</x><y>170</y></estadoCoord><estadoCoord><nombre>S5</nombre><x>322</x><y>329</y></estadoCoord></coordenadas></authomata>